Metadata-Version: 2.1
Name: flow_matching
Version: 1.0.10
Summary: Flow Matching for Generative Modeling
Home-page: https://github.com/facebookresearch/flow_matching
Author: Brian Karrer,David Lopez-Paz,Heli Ben-Hamu,Itai Gat,Marton Havasi,Matthew Le,Neta Shaul,Peter Holderrieth,Ricky T.Q. Chen,Yaron Lipman
Author-email: ylipman@meta.com
License: CC-by-NC
Classifier: Topic :: Scientific/Engineering :: Artificial Intelligence
Classifier: License :: OSI Approved :: MIT License
Requires-Python: >=3.9.0
License-File: LICENSE
Requires-Dist: numpy
Requires-Dist: torch
Requires-Dist: torchdiffeq
Provides-Extra: dev
Requires-Dist: pre-commit ; extra == 'dev'
Requires-Dist: black ==22.6.0 ; extra == 'dev'
Requires-Dist: usort ==1.0.4 ; extra == 'dev'
Requires-Dist: ufmt ==2.3.0 ; extra == 'dev'
Requires-Dist: flake8 ==7.0.0 ; extra == 'dev'
Requires-Dist: pydoclint ; extra == 'dev'
